galileo_observe/__init__.py
galileo_observe/async_handlers.py
galileo_observe/constants/__init__.py
galileo_observe/constants/routes.py
galileo_observe/handlers.py
galileo_observe/helpers/__init__.py
galileo_observe/helpers/api_key.py
galileo_observe/helpers/group.py
galileo_observe/helpers/group_integration.py
galileo_observe/helpers/group_project.py
galileo_observe/helpers/project.py
galileo_observe/helpers/user.py
galileo_observe/helpers/user_integration.py
galileo_observe/helpers/user_project.py
galileo_observe/login_module.py
galileo_observe/monitor.py
galileo_observe/schema/__init__.py
galileo_observe/schema/config.py
galileo_observe/schema/project.py
galileo_observe/schema/transaction.py
galileo_observe/utils/__init__.py
galileo_observe/utils/api_client.py
galileo_observe/utils/serialization.py
galileo_observe/workflow.py
galileo_observe-1.29.1.dist-info/LICENSE
galileo_observe-1.29.1.dist-info/METADATA
galileo_observe-1.29.1.dist-info/WHEEL
galileo_observe-1.29.1.dist-info/RECORD
