Metadata-Version: 2.3
Name: galileo-observe
Version: 1.29.1
Summary: 📈 Monitor your LLM integration with Galileo Observe!
License: Apache-2.0
Keywords: monitoring,nlp,llm,quality,language_models,galileo,artificial_intelligence,observability,generative_ai,galileo
Author: Galileo Technologies Inc.
Author-email: team@rungalileo.io
Requires-Python: >=3.9
Classifier: Development Status :: 5 - Production/Stable
Classifier: Framework :: Pydantic
Classifier: License :: OSI Approved :: Apache Software License
Classifier: Framework :: IPython
Classifier: Framework :: Jupyter
Classifier: Framework :: Jupyter :: JupyterLab
Classifier: Intended Audience :: Developers
Classifier: Intended Audience :: Information Technology
Classifier: Intended Audience :: Science/Research
Classifier: Operating System :: OS Independent
Classifier: Programming Language :: ML
Classifier: Programming Language :: Python :: 3 :: Only
Classifier: Programming Language :: Python :: 3.8
Classifier: Programming Language :: Python :: 3.9
Classifier: Programming Language :: Python :: 3.10
Classifier: Programming Language :: Python :: 3.11
Classifier: Programming Language :: Python :: 3.12
Classifier: Programming Language :: Python :: 3.13
Classifier: Programming Language :: Python :: 3.14
Classifier: Topic :: Scientific/Engineering :: Artificial Intelligence
Classifier: Topic :: Software Development :: Libraries
Classifier: Topic :: Software Development :: Libraries :: Python Modules
Classifier: Typing :: Typed
Provides-Extra: all
Provides-Extra: langchain
Requires-Dist: galileo-core (>=3.67.3,<4.0.0)
Requires-Dist: httpx (>0.27.0,<=0.29.0)
Requires-Dist: langchain-core ; extra == "all"
Requires-Dist: langchain-core ; extra == "langchain"
Requires-Dist: pydantic (>=2.11.7,<3.0.0)
Requires-Dist: pyjwt (>=2.8.0,<3.0.0)
Requires-Dist: pytz (>=2024,<2026)
Requires-Dist: tiktoken (>=0.7,<0.12)
